{"chunk_definitions":[{"row":17,"row_count":1,"visible":true,"expansion_state":0,"options":{"engine":"r","label":"setup","include":false,"dev":"png"},"document_id":"A1E1249C","chunk_id":"csetup_chunk","chunk_label":"setup"},{"row":254,"row_count":1,"visible":true,"expansion_state":0,"options":{"engine":"r","warning":false,"message":false,"label":"unnamed-chunk-57","dev":"png"},"document_id":"A1E1249C","chunk_id":"c4d8c23lmfp69","chunk_label":"unnamed-chunk-10"},{"row":281,"row_count":1,"visible":true,"expansion_state":0,"options":{"engine":"r","warning":false,"message":false,"label":"unnamed-chunk-62","dev":"png"},"document_id":"A1E1249C","chunk_id":"csuqevltprzfj","chunk_label":"unnamed-chunk-11"},{"row":311,"row_count":1,"visible":true,"expansion_state":0,"options":{"engine":"r","label":"unnamed-chunk-65","dev":"png"},"document_id":"A1E1249C","chunk_id":"cycqpn2xmm8ov","chunk_label":"unnamed-chunk-13"},{"row":350,"row_count":1,"visible":true,"expansion_state":0,"options":{"engine":"r","warning":false,"message":false,"label":"unnamed-chunk-68","dev":"png"},"document_id":"A1E1249C","chunk_id":"crevbdbji22e8","chunk_label":"unnamed-chunk-15"},{"row":476,"row_count":1,"visible":true,"expansion_state":0,"options":{"engine":"r","message":false,"warning":false,"label":"unnamed-chunk-10","dev":"png"},"document_id":"A1E1249C","chunk_id":"clvndx4wuf0f8","chunk_label":"unnamed-chunk-20"}],"doc_write_time":1725997082,"chunk_rendered_width":400}